README.txt
setup.cfg
setup.py
ObjectStateTracer.egg-info/PKG-INFO
ObjectStateTracer.egg-info/SOURCES.txt
ObjectStateTracer.egg-info/dependency_links.txt
ObjectStateTracer.egg-info/entry_points.txt
ObjectStateTracer.egg-info/not-zip-safe
ObjectStateTracer.egg-info/requires.txt
ObjectStateTracer.egg-info/top_level.txt
objectstatetracer/__init__.py
objectstatetracer/auth.py
objectstatetracer/base.py
objectstatetracer/controllers.py
objectstatetracer/decorators.py
objectstatetracer/exceptions.py
objectstatetracer/extension.py
objectstatetracer/model.py
objectstatetracer/registry.py
objectstatetracer/release.py
objectstatetracer/state.py
objectstatetracer/tests.py
objectstatetracer/util.py
objectstatetracer/widgets.py
objectstatetracer/static/css/history_panel.css
objectstatetracer/static/css/ost_menu.css
objectstatetracer/static/css/ost_notifier.css
objectstatetracer/static/images/check.gif
objectstatetracer/static/images/cross.gif
objectstatetracer/static/images/exclamation_mark.gif
objectstatetracer/static/images/favicon.ico
objectstatetracer/static/images/tg_under_the_hood.png
objectstatetracer/static/images/under_the_hood_blue.png
objectstatetracer/static/javascript/ost_menu.js
objectstatetracer/static/javascript/ost_notifier.js
objectstatetracer/templates/__init__.py
objectstatetracer/templates/history.kid
objectstatetracer/templates/master.kid
objectstatetracer/templates/ost_menu.kid
objectstatetracer/templates/ost_notifier.kid
objectstatetracer/templates/pendings.kid
objectstatetracer/templates/state_details.kid
